Metadata-Version: 2.1
Name: topsis-tanisha-101803042
Version: 1.2
Summary: Topsis Score and Rank generator
Home-page: https://github.com/Tanisha1508/topsis_tanisha_101803042
Author: Tanisha Garg
Author-email: tgarg_be18@thapar.edu
License: MIT
Download-URL: https://github.com/Tanisha1508/topsis_tanisha_101803042/archive/v1.2.tar.gz
Keywords: topsis,topsis score,rank,Thapar
Platform: UNKNOWN
Classifier: Development Status :: 5 - Production/Stable
Classifier: Intended Audience :: Developers
Classifier: Topic :: Software Development :: Build Tools
Classifier: License :: OSI Approved :: MIT License
Classifier: Programming Language :: Python :: 3.6
Classifier: Programming Language :: Python :: 3.8
